PyCode/__init__.py
your_unique_package_name-0.1.dist-info/METADATA
your_unique_package_name-0.1.dist-info/WHEEL
your_unique_package_name-0.1.dist-info/top_level.txt
your_unique_package_name-0.1.dist-info/RECORD
