Metadata-Version: 2.4
Name: your-unique-package-name
Version: 0.1
Summary: A beginner test package
Author: Your Name
Classifier: Programming Language :: Python :: 3
Dynamic: author
Dynamic: classifier
Dynamic: description
Dynamic: description-content-type
Dynamic: summary
